micalculadora/__init__.py
micalculadora/calculadora.py
micalculadora/operaciones.py
micalculadora_thelaw-0.1.0.dist-info/METADATA
micalculadora_thelaw-0.1.0.dist-info/WHEEL
micalculadora_thelaw-0.1.0.dist-info/top_level.txt
micalculadora_thelaw-0.1.0.dist-info/RECORD
